execlib/__init__.py
execlib/event.py
execlib/handler.py
execlib/listener.py
execlib/router.py
execlib/server.py
execlib/listeners/__init__.py
execlib/listeners/path.py
execlib/routers/__init__.py
execlib/routers/path.py
execlib/syncers/__init__.py
execlib/syncers/router.py
execlib/util/__init__.py
execlib/util/generic.py
execlib/util/path.py
execlib-0.4.4.dist-info/LICENSE
execlib-0.4.4.dist-info/METADATA
execlib-0.4.4.dist-info/WHEEL
execlib-0.4.4.dist-info/top_level.txt
execlib-0.4.4.dist-info/RECORD
