Metadata-Version: 2.1
Name: execlib
Version: 0.4.4
Summary: Lightweight multi-threaded job framework
Author-email: Sam Griesemer <samgriesemer+git@gmail.com>
Project-URL: Homepage, https://doc.olog.io/execlib
Project-URL: Documentation, https://doc.olog.io/execlib
Project-URL: Repository, https://git.olog.io/olog/execlib
Project-URL: Issues, https://git.olog.io/olog/execlib/issues
Keywords: concurrent,async,inotify
Classifier: Programming Language :: Python :: 3.12
Classifier: License :: OSI Approved :: MIT License
Classifier: Operating System :: OS Independent
Classifier: Development Status :: 3 - Alpha
Classifier: Intended Audience :: Developers
Requires-Python: >=3.12
License-File: LICENSE
Requires-Dist: tqdm
Requires-Dist: wcmatch
Requires-Dist: uvicorn
Requires-Dist: fastapi
Requires-Dist: colorama
Requires-Dist: starlette
Requires-Dist: inotify-simple
Provides-Extra: docs
Requires-Dist: sphinx ; extra == 'docs'
Requires-Dist: sphinx-togglebutton ; extra == 'docs'
Requires-Dist: sphinx-autodoc-typehints ; extra == 'docs'
Requires-Dist: furo ; extra == 'docs'
Requires-Dist: myst-parser ; extra == 'docs'
Provides-Extra: tests
Requires-Dist: pytest ; extra == 'tests'
Requires-Dist: websockets ; extra == 'tests'
